[
  {
    "time": "2025-10-04T13:27:15Z",
    "mgrs": "35VKH12345678",
    "what": "soldier",
    "amount": 1.0,
    "confidence": 80,
    "sensor_id": "uav-17",
    "unit": "Coy A",
    "observer_signature": "Sensor 1, Team A",
    "original_message": null
  },
  {
    "time": "2025-10-04T13:27:15Z",
    "mgrs": "35VKH12345678",
    "what": "camouflage_soldier",
    "amount": 1.0,
    "confidence": 63,
    "sensor_id": "uav-17",
    "unit": "Coy A",
    "observer_signature": "Sensor 1, Team A",
    "original_message": null
  },
  {
    "time": "2025-10-04T13:28:28Z",
    "mgrs": "35VKH12345678",
    "what": "soldier",
    "amount": 1.0,
    "confidence": 80,
    "sensor_id": "uav-17",
    "unit": "Coy A",
    "observer_signature": "Sensor 1, Team A",
    "original_message": null
  },
  {
    "time": "2025-10-04T13:28:28Z",
    "mgrs": "35VKH12345678",
    "what": "camouflage_soldier",
    "amount": 1.0,
    "confidence": 63,
    "sensor_id": "uav-17",
    "unit": "Coy A",
    "observer_signature": "Sensor 1, Team A",
    "original_message": null
  },
  {
    "time": "2025-10-04T13:29:05Z",
    "mgrs": "35VKH12345678",
    "what": "soldier",
    "amount": 1.0,
    "confidence": 80,
    "sensor_id": "uav-17",
    "unit": "Coy A",
    "observer_signature": "Sensor 1, Team A",
    "original_message": null
  },
  {
    "time": "2025-10-04T13:29:05Z",
    "mgrs": "35VKH12345678",
    "what": "camouflage_soldier",
    "amount": 1.0,
    "confidence": 63,
    "sensor_id": "uav-17",
    "unit": "Coy A",
    "observer_signature": "Sensor 1, Team A",
    "original_message": null
  },
  {
    "time": "2025-10-04T13:41:26Z",
    "mgrs": "35VKH12345678",
    "what": "soldier",
    "amount": 1.0,
    "confidence": 80,
    "sensor_id": "uav-17",
    "unit": "Coy A",
    "observer_signature": "Sensor 1, Team A",
    "original_message": null
  },
  {
    "time": "2025-10-04T13:41:26Z",
    "mgrs": "35VKH12345678",
    "what": "camouflage_soldier",
    "amount": 1.0,
    "confidence": 63,
    "sensor_id": "uav-17",
    "unit": "Coy A",
    "observer_signature": "Sensor 1, Team A",
    "original_message": null
  }
]